{
	"schema_version": 1,
	"quilt_loader": {
		"group": "de.pandro.QuiltTestMod",
		"id": "quilt_test_mod",
		"version": "1.0.0",
		"metadata": {
			"name": "Quilt Test Mod",
			"description": "My first Quilt mod.",
			"contributors": {
				"Pandro": "Owner/Developer"
			},
			"contact": {
				"homepage": "",
				"issues": "",
				"sources": ""
			},
			"icon": "assets/quilt_test_mod/icon.png"
		},
		"intermediate_mappings": "net.fabricmc:intermediary",
		"entrypoints": {
			"init": "de.pandro.QuiltTestMod.quilt_test_mod.QuiltTestMod"
		},
		"depends": [
			{
				"id": "quilt_loader",
				"versions": ">=0.19.1"
			},
			{
				"id": "quilted_fabric_api",
				"versions": ">=7.0.2"
			},
			{
				"id": "minecraft",
				"versions": ">=1.20"
			}
		]
	},
	"mixin": "quilt_test_mod.mixins.json"
}
